relike/__init__.py
relike/constants.py
relike/data_loader.py
relike/likelihood.py
relike/pc.py
relike/sample_xe.py
relike/second_helium.py
relike/data/pl18_zmax30/fiducial_cosmology.yaml
relike/data/pl18_zmax30/invcov.dat
relike/data/pl18_zmax30/mean.dat
relike/data/pl18_zmax30/pc.dat
relike/data/pl18_zmax30/taufid.dat
relike/data/pl18_zmax30/taufid_cumulative.dat
relike/data/pl18_zmax30/taumj.dat
relike/data/pl18_zmax30/taumj_cumulative.dat
relike/utils/__init__.py
relike/utils/file_tools.py
relike-0.0.4.dist-info/LICENSE.txt
relike-0.0.4.dist-info/METADATA
relike-0.0.4.dist-info/WHEEL
relike-0.0.4.dist-info/top_level.txt
relike-0.0.4.dist-info/RECORD
