Metadata-Version: 2.1
Name: relike
Version: 0.0.4
Summary: Python package for the Reionization Effective Likelihood (relike) from Planck data
Home-page: https://github.com/chenheinrich/relike
Author: Chen Heinrich
Author-email: chenhe@caltech.edu
License: UNKNOWN
Platform: UNKNOWN
Classifier: Programming Language :: Python
Classifier: Programming Language :: Python :: 3
Classifier: Programming Language :: Python :: 3.8
Classifier: License :: OSI Approved :: GNU General Public License v3 or later (GPLv3+)
Requires-Python: >=3.8
Requires-Dist: scipy (>=1.6.0)
Requires-Dist: numpy (>=1.18.5)
Requires-Dist: matplotlib (>=3.4.1)
Requires-Dist: pyyaml (>=5.3.1)
Requires-Dist: pytest (>=5.4.3)
